FreeWork
