Metadata-Version: 2.1
Name: FreeWork
Version: 1.0.10
Summary: 简单又实用的office操作函数！(Simple and practical office operation functions!)
Home-page: UNKNOWN
Author: Jhonie King(王骏诚)
Author-email: queenelsaofarendelle2022@gmail.com
License: MIT License
Keywords: python,Office,Excle,Word,File's operation
Platform: UNKNOWN
Classifier: Intended Audience :: Developers
Classifier: Operating System :: OS Independent
Classifier: Natural Language :: Chinese (Simplified)
Classifier: Programming Language :: Python
Classifier: Programming Language :: Python :: 2
Classifier: Programming Language :: Python :: 2.7
Classifier: Programming Language :: Python :: 3
Classifier: Programming Language :: Python :: 3.5
Classifier: Programming Language :: Python :: 3.6
Classifier: Programming Language :: Python :: 3.7
Classifier: Programming Language :: Python :: 3.8
Classifier: Topic :: Software Development :: Libraries
License-File: LICENSE.txt
